[
    {
        "username": "maddy17",
        "studentSchoolId": "123",
        "password": "password",
        "isAdmin": false
    },
    {
        "username": "kev",
        "studentSchoolId": "1234",
        "isAdmin": false,
        "password": "password"
    },
    {
        "username": "mike",
        "isAdmin": true,
        "password": "password"
    },
    {
        "username": "tracy",
        "studentSchoolId": "12345",
        "isAdmin": false,
        "password": "password"
    }
]